PowerPlatform/__init__.py
PowerPlatform/Dataverse/__init__.py
PowerPlatform/Dataverse/__version__.py
PowerPlatform/Dataverse/client.py
PowerPlatform/Dataverse/py.typed
PowerPlatform/Dataverse/core/__init__.py
PowerPlatform/Dataverse/core/_auth.py
PowerPlatform/Dataverse/core/_error_codes.py
PowerPlatform/Dataverse/core/_http.py
PowerPlatform/Dataverse/core/config.py
PowerPlatform/Dataverse/core/errors.py
PowerPlatform/Dataverse/data/__init__.py
PowerPlatform/Dataverse/data/_odata.py
PowerPlatform/Dataverse/data/_upload.py
PowerPlatform/Dataverse/extensions/__init__.py
PowerPlatform/Dataverse/models/__init__.py
PowerPlatform/Dataverse/utils/__init__.py
powerplatform_dataverse_client-0.1.0b3.dist-info/licenses/LICENSE
powerplatform_dataverse_client-0.1.0b3.dist-info/METADATA
powerplatform_dataverse_client-0.1.0b3.dist-info/WHEEL
powerplatform_dataverse_client-0.1.0b3.dist-info/top_level.txt
powerplatform_dataverse_client-0.1.0b3.dist-info/RECORD
