Metadata-Version: 2.4
Name: PowerPlatform-Dataverse-Client
Version: 0.1.0b3
Summary: Python SDK for Microsoft Dataverse
Author: Microsoft Corporation
License-Expression: MIT
Project-URL: Homepage, https://github.com/microsoft/PowerPlatform-DataverseClient-Python
Project-URL: Repository, https://github.com/microsoft/PowerPlatform-DataverseClient-Python.git
Project-URL: Issues, https://github.com/microsoft/PowerPlatform-DataverseClient-Python/issues
Project-URL: Documentation, https://github.com/microsoft/PowerPlatform-DataverseClient-Python#readme
Keywords: dataverse,powerapps,powerplatform,crm,dynamics,odata
Classifier: Development Status :: 4 - Beta
Classifier: Intended Audience :: Developers
Classifier: Programming Language :: Python :: 3
Classifier: Programming Language :: Python :: 3.10
Classifier: Programming Language :: Python :: 3.11
Classifier: Programming Language :: Python :: 3.12
Classifier: Programming Language :: Python :: 3.13
Classifier: Programming Language :: Python :: 3.14
Classifier: Operating System :: OS Independent
Classifier: Topic :: Software Development :: Libraries :: Python Modules
Classifier: Typing :: Typed
Requires-Python: >=3.10
License-File: LICENSE
Requires-Dist: azure-identity>=1.17.0
Requires-Dist: azure-core>=1.30.2
Requires-Dist: requests>=2.32.0
Provides-Extra: dev
Requires-Dist: pytest>=7.0.0; extra == "dev"
Requires-Dist: pytest-cov>=4.0.0; extra == "dev"
Requires-Dist: black>=23.0.0; extra == "dev"
Requires-Dist: isort>=5.12.0; extra == "dev"
Requires-Dist: mypy>=1.0.0; extra == "dev"
Requires-Dist: ruff>=0.1.0; extra == "dev"
Dynamic: license-file
